docs/conf.py
docs/contributing.rst
docs/index.rst
docs/installation.rst
docs/modules.rst
docs/_static/images/speakerbox-example-video-screenshot.png
docs/_static/images/workflow.png
paper/paper.bib
paper/paper.md
speakerbox/__init__.py
speakerbox/examples.py
speakerbox/main.py
speakerbox/preprocess.py
speakerbox/py.typed
speakerbox/types.py
speakerbox/utils.py
speakerbox/tests/__init__.py
speakerbox/tests/conftest.py
speakerbox/tests/test_preprocess.py
speakerbox/tests/test_train.py
speakerbox/tests/data/__init__.py
speakerbox/tests/data/diarized.zip
speakerbox/tests/data/short_0.wav
speakerbox/tests/data/short_1.wav
speakerbox/tests/data/short_2.wav
speakerbox-1.2.0.dist-info/LICENSE
speakerbox-1.2.0.dist-info/METADATA
speakerbox-1.2.0.dist-info/WHEEL
speakerbox-1.2.0.dist-info/top_level.txt
speakerbox-1.2.0.dist-info/RECORD
