Metadata-Version: 2.1
Name: speakerbox
Version: 1.2.0
Summary: Few-Shot Speaker Identification Model Training and Application
Author-email: Eva Maxfield Brown <evamaxfieldbrown@gmail.com>
License: MIT License
Project-URL: Homepage, https://github.com/CouncilDataProject/speakerbox
Project-URL: Bug Tracker, https://github.com/CouncilDataProject/speakerbox/issues
Project-URL: Documentation, https://CouncilDataProject.github.io/speakerbox
Project-URL: User Support, https://github.com/CouncilDataProject/speakerbox/issues
Classifier: Development Status :: 4 - Beta
Classifier: Natural Language :: English
Classifier: Programming Language :: Python :: 3.8
Classifier: Programming Language :: Python :: 3.9
Classifier: Programming Language :: Python :: 3.10
Requires-Python: >=3.8
License-File: LICENSE
Requires-Dist: dataclasses-json (~=0.5)
Requires-Dist: datasets[audio] (~=1.18)
Requires-Dist: librosa (~=0.8)
Requires-Dist: matplotlib (~=3.5)
Requires-Dist: pandas (~=1.0)
Requires-Dist: pydub (~=0.25)
Requires-Dist: scikit-learn (~=1.0)
Requires-Dist: speechbrain (~=0.5.11)
Requires-Dist: torch (~=1.10)
Requires-Dist: torchaudio (~=0.10)
Requires-Dist: transformers (~=4.16)
Requires-Dist: pyannote.audio (~=2.1)
Provides-Extra: dev
Requires-Dist: ipython (>=8.4.0) ; extra == 'dev'
Requires-Dist: tabulate ; extra == 'dev'
Provides-Extra: docs
Requires-Dist: m2r2 (>=0.2.7) ; extra == 'docs'
Requires-Dist: Sphinx (>=4.0.0) ; extra == 'docs'
Requires-Dist: furo (>=2022.4.7) ; extra == 'docs'
Requires-Dist: numpydoc ; extra == 'docs'
Requires-Dist: sphinx-copybutton ; extra == 'docs'
Requires-Dist: docutils (<0.19,>=0.18) ; extra == 'docs'
Provides-Extra: example_data
Requires-Dist: gdown (~=4.6) ; extra == 'example_data'
Provides-Extra: lint
Requires-Dist: black (>=22.3.0) ; extra == 'lint'
Requires-Dist: cdp-backend (~=3.0.3) ; extra == 'lint'
Requires-Dist: cdp-data (~=0.0.6) ; extra == 'lint'
Requires-Dist: check-manifest (>=0.48) ; extra == 'lint'
Requires-Dist: ruff (>=0.0.216) ; extra == 'lint'
Requires-Dist: mypy (>=0.790) ; extra == 'lint'
Requires-Dist: pre-commit (>=2.20.0) ; extra == 'lint'
Provides-Extra: test
Requires-Dist: cdp-backend (~=3.0.3) ; extra == 'test'
Requires-Dist: coverage (>=5.1) ; extra == 'test'
Requires-Dist: pytest (>=5.4.3) ; extra == 'test'
Requires-Dist: pytest-cov (>=2.9.0) ; extra == 'test'
Requires-Dist: pytest-raises (>=0.11) ; extra == 'test'
